{"metadata": {"data_version": "5", "match_id": "KR_6265738451", "participants": ["4Jy8YwCmeeM4Hq_CTofzouow7YurClOG3yk72IFTCoK1Wh2LoQ490Z6iJiATniUHNoH5zu9CO0OgeA", "iZaT4F_CsbiBP_5O17fCR3qK4aKjhHIz6yVZLlBHXFtcq56H9WPic7CDcxutbuVD1DemCRHZNcKyww", "mSqcv_nWu9PqIlxA0pPZE53bckYhfZwejqNYj_25gCXlYIN05ue0FCfzfHwmTD1WR0klrMrUyzgKkA", "r6jMzrmo1X1lWKkCNoaBHKiKJNykuA9WgOx-pl5rbExMngbkdaeORMyRY0jIkHRuSOg5pIHMII-Ujg", "YpJNfXy9ov0tRJIJWlZngqxy9E4gFDXVkvSdkaE7LDxJpToRyZiCEw8ko_TtnSDQhx-azOB1aZQmoQ", "bTXe7Ua8k2yrwiy3wfWK_C7KZcMBp6pEcdfrWgrZEJsa2a5_BAvgwtYEa7B50XwBNluPJiTa879qRQ", "snQmVmhvAH9DU7WnwDp6HWls0EeWzAEsMQCy4pSv5FDcWRbBtl-XEjc1s037Wn8iximXzCQYR2BO2A", "76_xmZTvITYPw4apY0JQ5XTIL2YxJtGwGZi1P-cmNMPAmtg8-tCDXVSXoOIjlNg3wlTzy7NaiaRTYA"]}, "info": {"game_datetime": 1671357875798, "game_length": 1933.8399658203125, "game_version": "Version 12.23.483.5208 (Dec 05 2022/14:03:09) [PUBLIC] <Releases/12.23>", "participants": [{"augments": ["TFT8_Augment_UndergroundTheTrait", "TFT6_Augment_PortableForge", "TFT6_Augment_ComponentGrabBag"], "companion": {"content_ID": "bdc701a6-2027-4610-ade0-1f0886938a6a", "item_ID": 42021, "skin_ID": 21, "species": "PetDuckbill"}, "gold_left": 3, "last_round": 23, "level": 8, "placement": 8, "players_eliminated": 0, "puuid": "4Jy8YwCmeeM4Hq_CTofzouow7YurClOG3yk72IFTCoK1Wh2LoQ490Z6iJiATniUHNoH5zu9CO0OgeA", "time_eliminated": 1340.7027587890625, "total_damage_to_players": 32, "traits": [{"name": "Set8_Ace", "num_units": 1, "style": 1, "tier_current": 1, "tier_total": 2}, {"name": "Set8_Aegis", "num_units": 4, "style": 3, "tier_current": 3, "tier_total": 4}, {"name": "Set8_Brawler", "num_units": 2, "style": 1, "tier_current": 1, "tier_total": 4}, {"name": "Set8_Channeler", "num_units": 1, "style": 0, "tier_current": 0, "tier_total": 4}, {"name": "Set8_Civilian", "num_units": 1, "style": 1, "tier_current": 1, "tier_total": 3}, {"name": "Set8_Deadeye", "num_units": 1, "style": 0, "tier_current": 0, "tier_total": 2}, {"name": "Set8_ExoPrime", "num_units": 1, "style": 0, "tier_current": 0, "tier_total": 2}, {"name": "Set8_Forecaster", "num_units": 1, "style": 3, "tier_current": 1, "tier_total": 1}, {"name": "Set8_Mascot", "num_units": 1, "style": 0, "tier_current": 0, "tier_total": 4}, {"name": "Set8_OxForce", "num_units": 1, "style": 0, "tier_current": 0, "tier_total": 4}, {"name": "Set8_Prankster", "num_units": 1, "style": 0, "tier_current": 0, "tier_total": 2}, {"name": "Set8_Renegade", "num_units": 1, "style": 0, "tier_current": 0, "tier_total": 2}, {"name": "Set8_SpaceCorps", "num_units": 1, "style": 0, "tier_current": 0, "tier_total": 3}, {"name": "Set8_StarGuardian", "num_units": 1, "style": 0, "tier_current": 0, "tier_total": 4}, {"name": "Set8_Threat", "num_units": 1, "style": 0, "tier_current": 1, "tier_total": 1}, {"name": "Set8_UndergroundThe", "num_units": 3, "style": 1, "tier_current": 1, "tier_total": 2}], "units": [{"character_id": "TFT8_Vi", "itemNames": [], "items": [], "name": "", "rarity": 1, "tier": 2}, {"character_id": "TFT8_Alistar", "itemNames": [], "items": [], "name": "", "rarity": 2, "tier": 1}, {"character_id": "TFT8_Ekko", "itemNames": [], "items": [], "name": "", "rarity": 4, "tier": 1}, {"character_id": "TFT8_Samira", "itemNames": ["TFT_Item_LastWhisper", "TFT4_Item_OrnnTheCollector", "TFT_Item_MadredsBloodrazor"], "items": [29, 9009, 12], "name": "", "rarity": 4, "tier": 2}, {"character_id": "TFT8_AurelionSol", "itemNames": ["TFT_Item_JeweledGauntlet", "TFT_Item_SpearOfShojin", "TFT_Item_MadredsBloodrazor"], "items": [39, 14, 12], "name": "", "rarity": 4, "tier": 1}, {"character_id": "TFT8_Sejuani", "itemNames": ["TFT_Item_WarmogsArmor"], "items": [77], "name": "", "rarity": 4, "tier": 1}, {"character_id": "TFT8_Janna", "itemNames": [], "items": [], "name": "", "rarity": 6, "tier": 1}, {"character_id": "TFT8_Leona", "itemNames": ["TFT_Item_Bloodthirster", "TFT_Item_WarmogsArmor"], "items": [16, 77], "name": "", "rarity": 6, "tier": 1}]}, {"augments": ["TFT7_Augment_Preparation2", "TFT6_Augment_TradeSectorPlus", "TFT8_Augment_MascotEmblem"], "companion": {"content_ID": "50e8746e-3e65-4463-8938-0fbadd0c00d7", "item_ID": 10016, "skin_ID": 16, "species": "PetSGCat"}, "gold_left": 1, "last_round": 33, "level": 9, "placement": 1, "players_eliminated": 3, "puuid": "iZaT4F_CsbiBP_5O17fCR3qK4aKjhHIz6yVZLlBHXFtcq56H9WPic7CDcxutbuVD1DemCRHZNcKyww", "time_eliminated": 1925.677978515625, "total_damage_to_players": 186, "traits": [{"name": "Set8_Aegis", "num_units": 2, "style": 1, "tier_current": 1, "tier_total": 4}, {"name": "Set8_AnimaSquad", "num_units": 1, "style": 0, "tier_current": 0, "tier_total": 3}, {"name": "Set8_Brawler", "num_units": 2, "style": 1, "tier_current": 1, "tier_total": 4}, {"name": "Set8_Civilian", "num_units": 1, "style": 1, "tier_current": 1, "tier_total": 3}, {"name": "Set8_Duelist", "num_units": 1, "style": 0, "tier_current": 0, "tier_total": 4}, {"name": "Set8_Heart", "num_units": 2, "style": 1, "tier_current": 1, "tier_total": 3}, {"name": "Set8_Mascot", "num_units": 6, "style": 3, "tier_current": 3, "tier_total": 4}, {"name": "Set8_OxForce", "num_units": 1, "style": 0, "tier_current": 0, "tier_total": 4}, {"name": "Set8_StarGuardian", "num_units": 1, "style": 0, "tier_current": 0, "tier_total": 4}, {"name": "Set8_Supers", "num_units": 3, "style": 3, "tier_current": 1, "tier_total": 1}, {"name": "Set8_UndergroundThe", "num_units": 1, "style": 0, "tier_current": 0, "tier_total": 2}], "units": [{"character_id": "TFT8_Galio", "itemNames": [], "items": [], "name": "", "rarity": 0, "tier": 2}, {"character_id": "TFT8_Nasus", "itemNames": [], "items": [], "name": "", "rarity": 0, "tier": 3}, {"character_id": "TFT8_Gangplank", "itemNames": ["TFT_Item_UnstableConcoction"], "items": [49], "name": "", "rarity": 0, "tier": 3}, {"character_id": "TFT8_Vi", "itemNames": [], "items": [], "name": "", "rarity": 1, "tier": 1}, {"character_id": "TFT8_LeeSin", "itemNames": ["TFT8_Item_MascotEmblemItem", "TFT_Item_TitanicHydra", "TFT_Item_DragonsClaw"], "items": [8008, 27, 66], "name": "", "rarity": 1, "tier": 3}, {"character_id": "TFT8_Malphite", "itemNames": ["TFT_Item_GargoyleStoneplate", "TFT_Item_RedBuff"], "items": [56, 57], "name": "", "rarity": 1, "tier": 3}, {"character_id": "TFT8_Yuumi", "itemNames": ["TFT_Item_RabadonsDeathcap", "TFT_Item_SeraphsEmbrace", "TFT_Item_JeweledGauntlet"], "items": [33, 44, 39], "name": "", "rarity": 1, "tier": 3}, {"character_id": "TFT8_Yuumi", "itemNames": [], "items": [], "name": "", "rarity": 1, "tier": 1}, {"character_id": "TFT8_Alistar", "itemNames": [], "items": [], "name": "", "rarity": 2, "tier": 2}]}, {"augments": ["TFT6_Augment_TrueTwos", "TFT6_Augment_PortableForge", "TFT6_Augment_ThrillOfTheHunt2"], "companion": {"content_ID": "a07ffad0-7c04-4728-8474-27d0b074627b", "item_ID": 45002, "skin_ID": 2, "species": "PetChibiKaisa"}, "gold_left": 1, "last_round": 30, "level": 8, "placement": 5, "players_eliminated": 0, "puuid": "mSqcv_nWu9PqIlxA0pPZE53bckYhfZwejqNYj_25gCXlYIN05ue0FCfzfHwmTD1WR0klrMrUyzgKkA", "time_eliminated": 1750.0970458984375, "total_damage_to_players": 77, "traits": [{"name": "Set8_Ace", "num_units": 1, "style": 1, "tier_current": 1, "tier_total": 2}, {"name": "Set8_Aegis", "num_units": 3, "style": 2, "tier_current": 2, "tier_total": 4}, {"name": "Set8_Arsenal", "num_units": 1, "style": 3, "tier_current": 1, "tier_total": 1}, {"name": "Set8_Brawler", "num_units": 2, "style": 1, "tier_current": 1, "tier_total": 4}, {"name": "Set8_Deadeye", "num_units": 2, "style": 1, "tier_current": 1, "tier_total": 2}, {"name": "Set8_GenAE", "num_units": 1, "style": 0, "tier_current": 0, "tier_total": 2}, {"name": "Set8_Mascot", "num_units": 2, "style": 1, "tier_current": 1, "tier_total": 4}, {"name": "Set8_OxForce", "num_units": 2, "style": 1, "tier_current": 1, "tier_total": 4}, {"name": "Set8_Prankster", "num_units": 1, "style": 0, "tier_current": 0, "tier_total": 2}, {"name": "Set8_SpaceCorps", "num_units": 1, "style": 0, "tier_current": 0, "tier_total": 3}, {"name": "Set8_StarGuardian", "num_units": 1, "style": 0, "tier_current": 0, "tier_total": 4}, {"name": "Set8_Threat", "num_units": 1, "style": 0, "tier_current": 1, "tier_total": 1}, {"name": "Set8_UndergroundThe", "num_units": 2, "style": 0, "tier_current": 0, "tier_total": 2}], "units": [{"character_id": "TFT8_Vi", "itemNames": [], "items": [], "name": "", "rarity": 1, "tier": 2}, {"character_id": "TFT8_Alistar", "itemNames": ["TFT_Item_Zephyr"], "items": [67], "name": "", "rarity": 2, "tier": 1}, {"character_id": "TFT8_Ekko", "itemNames": ["TFT_Item_Zephyr"], "items": [67], "name": "", "rarity": 4, "tier": 2}, {"character_id": "TFT8_Samira", "itemNames": ["TFT4_Item_OrnnObsidianCleaver", "TFT_Item_MadredsBloodrazor", "TFT_Item_InfinityEdge"], "items": [9006, 12, 19], "name": "", "rarity": 4, "tier": 2}, {"character_id": "TFT8_Zac", "itemNames": ["TFT_Item_BrambleVest", "TFT_Item_WarmogsArmor", "TFT_Item_RedBuff"], "items": [55, 77, 57], "name": "", "rarity": 4, "tier": 1}, {"character_id": "TFT8_Sejuani", "itemNames": [], "items": [], "name": "", "rarity": 4, "tier": 1}, {"character_id": "TFT8_Nunu", "itemNames": ["TFT_Item_ZekesHerald"], "items": [17], "name": "", "rarity": 6, "tier": 1}, {"character_id": "TFT8_Aphelios", "itemNames": [], "items": [], "name": "", "rarity": 6, "tier": 1}]}, {"augments": ["TFT6_Augment_TomeOfTraits1", "TFT6_Augment_TradeSectorPlus", "TFT7_Augment_AxiomArc2"], "companion": {"content_ID": "9bed4a77-2a3a-41ae-93d8-45dd597d173e", "item_ID": 29007, "skin_ID": 7, "species": "PetDowsie"}, "gold_left": 0, "last_round": 31, "level": 8, "placement": 3, "players_eliminated": 1, "puuid": "r6jMzrmo1X1lWKkCNoaBHKiKJNykuA9WgOx-pl5rbExMngbkdaeORMyRY0jIkHRuSOg5pIHMII-Ujg", "time_eliminated": 1812.8057861328125, "total_damage_to_players": 84, "traits": [{"name": "Set8_Admin", "num_units": 2, "style": 1, "tier_current": 1, "tier_total": 3}, {"name": "Set8_Aegis", "num_units": 2, "style": 1, "tier_current": 1, "tier_total": 4}, {"name": "Set8_Channeler", "num_units": 2, "style": 1, "tier_current": 1, "tier_total": 4}, {"name": "Set8_GenAE", "num_units": 3, "style": 1, "tier_current": 1, "tier_total": 2}, {"name": "Set8_Hacker", "num_units": 2, "style": 1, "tier_current": 1, "tier_total": 3}, {"name": "Set8_Heart", "num_units": 2, "style": 1, "tier_current": 1, "tier_total": 3}, {"name": "Set8_Mascot", "num_units": 1, "style": 0, "tier_current": 0, "tier_total": 4}, {"name": "Set8_OxForce", "num_units": 2, "style": 1, "tier_current": 1, "tier_total": 4}, {"name": "Set8_Prankster", "num_units": 3, "style": 3, "tier_current": 2, "tier_total": 2}, {"name": "Set8_StarGuardian", "num_units": 1, "style": 0, "tier_current": 0, "tier_total": 4}, {"name": "Set8_Threat", "num_units": 1, "style": 0, "tier_current": 1, "tier_total": 1}], "units": [{"character_id": "TFT8_Lulu", "itemNames": [], "items": [], "name": "", "rarity": 0, "tier": 2}, {"character_id": "TFT8_Annie", "itemNames": ["TFT_Item_GargoyleStoneplate"], "items": [56], "name": "", "rarity": 1, "tier": 2}, {"character_id": "TFT8_Alistar", "itemNames": ["TFT8_Item_PranksterEmblemItem"], "items": [8017], "name": "", "rarity": 2, "tier": 3}, {"character_id": "TFT8_Zoe", "itemNames": ["TFT_Item_UnstableConcoction", "TFT_Item_Morellonomicon", "TFT8_Item_GiantSlayer_GenAE"], "items": [49, 37, 9011], "name": "", "rarity": 2, "tier": 3}, {"character_id": "TFT8_Leblanc", "itemNames": ["TFT_Item_SpearOfShojin", "TFT_Item_JeweledGauntlet", "TFT_Item_TitansResolve"], "items": [14, 39, 25], "name": "", "rarity": 2, "tier": 3}, {"character_id": "TFT8_Ekko", "itemNames": [], "items": [], "name": "", "rarity": 4, "tier": 1}, {"character_id": "TFT8_Zac", "itemNames": [], "items": [], "name": "", "rarity": 4, "tier": 1}, {"character_id": "TFT8_Soraka", "itemNames": ["TFT_Item_StatikkShiv"], "items": [24], "name": "", "rarity": 4, "tier": 2}]}, {"augments": ["TFT6_Augment_SunfireBoard", "TFT6_Augment_SalvageBin", "TFT8_Augment_ADMINEmblem"], "companion": {"content_ID": "75180b95-663a-4385-836f-b134da2d1628", "item_ID": 19, "skin_ID": 19, "species": "PetTFTAvatar"}, "gold_left": 1, "last_round": 28, "level": 8, "placement": 6, "players_eliminated": 1, "puuid": "YpJNfXy9ov0tRJIJWlZngqxy9E4gFDXVkvSdkaE7LDxJpToRyZiCEw8ko_TtnSDQhx-azOB1aZQmoQ", "time_eliminated": 1652.280029296875, "total_damage_to_players": 90, "traits": [{"name": "Set8_Admin", "num_units": 4, "style": 3, "tier_current": 2, "tier_total": 3}, {"name": "Set8_Brawler", "num_units": 2, "style": 1, "tier_current": 1, "tier_total": 4}, {"name": "Set8_Channeler", "num_units": 2, "style": 1, "tier_current": 1, "tier_total": 4}, {"name": "Set8_Hacker", "num_units": 1, "style": 0, "tier_current": 0, "tier_total": 3}, {"name": "Set8_Heart", "num_units": 2, "style": 1, "tier_current": 1, "tier_total": 3}, {"name": "Set8_SpaceCorps", "num_units": 1, "style": 0, "tier_current": 0, "tier_total": 3}, {"name": "Set8_Threat", "num_units": 3, "style": 0, "tier_current": 1, "tier_total": 1}, {"name": "Set8_UndergroundThe", "num_units": 1, "style": 0, "tier_current": 0, "tier_total": 2}], "units": [{"character_id": "TFT8_Blitzcrank", "itemNames": [], "items": [], "name": "", "rarity": 0, "tier": 1}, {"character_id": "TFT8_Sona", "itemNames": ["TFT8_Item_ADMINEmblemItem"], "items": [8007], "name": "", "rarity": 2, "tier": 2}, {"character_id": "TFT8_Leblanc", "itemNames": ["TFT_Item_MadredsBloodrazor"], "items": [12], "name": "", "rarity": 2, "tier": 1}, {"character_id": "TFT8_AurelionSol", "itemNames": ["TFT_Item_ThiefsGloves", "TFT_Item_PowerGauntlet", "TFT_Item_FrozenHeart"], "items": [99, 79, 45], "name": "", "rarity": 4, "tier": 2}, {"character_id": "TFT8_Zac", "itemNames": ["TFT_Item_DragonsClaw", "TFT_Item_IonicSpark", "TFT_Item_WarmogsArmor"], "items": [66, 36, 77], "name": "", "rarity": 4, "tier": 2}, {"character_id": "TFT8_Sejuani", "itemNames": ["TFT_Item_DragonsClaw"], "items": [66], "name": "", "rarity": 4, "tier": 1}, {"character_id": "TFT8_Soraka", "itemNames": ["TFT_Item_JeweledGauntlet", "TFT_Item_MadredsBloodrazor"], "items": [39, 12], "name": "", "rarity": 4, "tier": 2}, {"character_id": "TFT8_Urgot", "itemNames": [], "items": [], "name": "", "rarity": 6, "tier": 1}]}, {"augments": ["TFT8_Augment_OxForceEmblem", "TFT6_Augment_CelestialBlessing2", "TFT6_Augment_ComponentGrabBag"], "companion": {"content_ID": "c4901af8-9abc-44ab-9c32-6c84c8041acf", "item_ID": 11017, "skin_ID": 17, "species": "PetSGPig"}, "gold_left": 0, "last_round": 24, "level": 8, "placement": 7, "players_eliminated": 0, "puuid": "bTXe7Ua8k2yrwiy3wfWK_C7KZcMBp6pEcdfrWgrZEJsa2a5_BAvgwtYEa7B50XwBNluPJiTa879qRQ", "time_eliminated": 1413.9443359375, "total_damage_to_players": 45, "traits": [{"name": "Set8_Ace", "num_units": 1, "style": 1, "tier_current": 1, "tier_total": 2}, {"name": "Set8_Aegis", "num_units": 2, "style": 1, "tier_current": 1, "tier_total": 4}, {"name": "Set8_Arsenal", "num_units": 1, "style": 3, "tier_current": 1, "tier_total": 1}, {"name": "Set8_Channeler", "num_units": 1, "style": 0, "tier_current": 0, "tier_total": 4}, {"name": "Set8_Deadeye", "num_units": 2, "style": 1, "tier_current": 1, "tier_total": 2}, {"name": "Set8_GenAE", "num_units": 1, "style": 0, "tier_current": 0, "tier_total": 2}, {"name": "Set8_Mascot", "num_units": 1, "style": 0, "tier_current": 0, "tier_total": 4}, {"name": "Set8_OxForce", "num_units": 6, "style": 3, "tier_current": 3, "tier_total": 4}, {"name": "Set8_Prankster", "num_units": 1, "style": 0, "tier_current": 0, "tier_total": 2}, {"name": "Set8_Renegade", "num_units": 2, "style": 0, "tier_current": 0, "tier_total": 2}, {"name": "Set8_StarGuardian", "num_units": 1, "style": 0, "tier_current": 0, "tier_total": 4}, {"name": "Set8_Threat", "num_units": 1, "style": 0, "tier_current": 1, "tier_total": 1}, {"name": "Set8_UndergroundThe", "num_units": 1, "style": 0, "tier_current": 0, "tier_total": 2}], "units": [{"character_id": "TFT8_Talon", "itemNames": [], "items": [], "name": "", "rarity": 0, "tier": 2}, {"character_id": "TFT8_Annie", "itemNames": ["TFT_Item_GargoyleStoneplate"], "items": [56], "name": "", "rarity": 1, "tier": 2}, {"character_id": "TFT8_Alistar", "itemNames": [], "items": [], "name": "", "rarity": 2, "tier": 1}, {"character_id": "TFT8_BelVeth", "itemNames": ["TFT_Item_LastWhisper", "TFT_Item_MadredsBloodrazor", "TFT8_Item_OxForceEmblemItem"], "items": [29, 12, 8004], "name": "", "rarity": 4, "tier": 2}, {"character_id": "TFT8_Ekko", "itemNames": [], "items": [], "name": "", "rarity": 4, "tier": 2}, {"character_id": "TFT8_Viego", "itemNames": ["TFT_Item_JeweledGauntlet", "TFT_Item_RabadonsDeathcap", "TFT_Item_JeweledGauntlet"], "items": [39, 33, 39], "name": "", "rarity": 4, "tier": 1}, {"character_id": "TFT8_Samira", "itemNames": [], "items": [], "name": "", "rarity": 4, "tier": 1}, {"character_id": "TFT8_Aphelios", "itemNames": [], "items": [], "name": "", "rarity": 6, "tier": 1}]}, {"augments": ["TFT6_Augment_TradeSector", "TFT6_Augment_CelestialBlessing2", "TFT6_Augment_TomeOfTraits1"], "companion": {"content_ID": "1388361c-a31c-499a-826f-26efdc8c1dbd", "item_ID": 9027, "skin_ID": 27, "species": "PetSpiritFox"}, "gold_left": 0, "last_round": 33, "level": 8, "placement": 2, "players_eliminated": 0, "puuid": "snQmVmhvAH9DU7WnwDp6HWls0EeWzAEsMQCy4pSv5FDcWRbBtl-XEjc1s037Wn8iximXzCQYR2BO2A", "time_eliminated": 1925.677978515625, "total_damage_to_players": 119, "traits": [{"name": "Set8_AnimaSquad", "num_units": 1, "style": 0, "tier_current": 0, "tier_total": 3}, {"name": "Set8_Brawler", "num_units": 1, "style": 0, "tier_current": 0, "tier_total": 4}, {"name": "Set8_Duelist", "num_units": 6, "style": 3, "tier_current": 3, "tier_total": 4}, {"name": "Set8_GenAE", "num_units": 1, "style": 0, "tier_current": 0, "tier_total": 2}, {"name": "Set8_Hacker", "num_units": 2, "style": 1, "tier_current": 1, "tier_total": 3}, {"name": "Set8_OxForce", "num_units": 1, "style": 0, "tier_current": 0, "tier_total": 4}, {"name": "Set8_Prankster", "num_units": 1, "style": 0, "tier_current": 0, "tier_total": 2}, {"name": "Set8_Recon", "num_units": 1, "style": 0, "tier_current": 0, "tier_total": 3}, {"name": "Set8_SpaceCorps", "num_units": 4, "style": 1, "tier_current": 1, "tier_total": 3}, {"name": "Set8_StarGuardian", "num_units": 1, "style": 0, "tier_current": 0, "tier_total": 4}, {"name": "Set8_Supers", "num_units": 1, "style": 0, "tier_current": 0, "tier_total": 1}], "units": [{"character_id": "TFT8_Gangplank", "itemNames": [], "items": [], "name": "", "rarity": 0, "tier": 2}, {"character_id": "TFT8_Fiora", "itemNames": [], "items": [], "name": "", "rarity": 1, "tier": 2}, {"character_id": "TFT8_Yasuo", "itemNames": ["TFT_Item_TitansResolve", "TFT_Item_JeweledGauntlet", "TFT_Item_Bloodthirster"], "items": [25, 39, 16], "name": "", "rarity": 1, "tier": 3}, {"character_id": "TFT8_Vayne", "itemNames": ["TFT8_Item_InterPolarisEmblemItem"], "items": [8003], "name": "", "rarity": 2, "tier": 2}, {"character_id": "TFT8_Nilah", "itemNames": ["TFT_Item_RedBuff"], "items": [57], "name": "", "rarity": 2, "tier": 2}, {"character_id": "TFT8_Zoe", "itemNames": [], "items": [], "name": "", "rarity": 2, "tier": 2}, {"character_id": "TFT8_Zed", "itemNames": ["TFT_Item_GuardianAngel", "TFT_Item_InfinityEdge", "TFT_Item_UnstableConcoction"], "items": [94, 19, 49], "name": "", "rarity": 4, "tier": 2}, {"character_id": "TFT8_Sejuani", "itemNames": ["TFT_Item_TitanicHydra"], "items": [27], "name": "", "rarity": 4, "tier": 2}]}, {"augments": ["TFT6_Augment_Ascension", "TFT6_Augment_RichGetRicherPlus", "TFT6_Augment_ThrillOfTheHunt2"], "companion": {"content_ID": "d6593334-1e30-4eb1-907c-f6427139be4d", "item_ID": 18, "skin_ID": 18, "species": "PetTFTAvatar"}, "gold_left": 3, "last_round": 30, "level": 7, "placement": 4, "players_eliminated": 1, "puuid": "76_xmZTvITYPw4apY0JQ5XTIL2YxJtGwGZi1P-cmNMPAmtg8-tCDXVSXoOIjlNg3wlTzy7NaiaRTYA", "time_eliminated": 1751.86328125, "total_damage_to_players": 101, "traits": [{"name": "Set8_Civilian", "num_units": 1, "style": 1, "tier_current": 1, "tier_total": 3}, {"name": "Set8_Deadeye", "num_units": 2, "style": 1, "tier_current": 1, "tier_total": 2}, {"name": "Set8_Threat", "num_units": 6, "style": 0, "tier_current": 1, "tier_total": 1}], "units": [{"character_id": "TFT8_Sivir", "itemNames": [], "items": [], "name": "", "rarity": 1, "tier": 2}, {"character_id": "TFT8_Velkoz", "itemNames": ["TFT_Item_HextechGunblade", "TFT_Item_ArchangelsStaff"], "items": [13, 34], "name": "", "rarity": 2, "tier": 2}, {"character_id": "TFT8_Chogath", "itemNames": ["TFT_Item_DragonsClaw", "TFT_Item_WarmogsArmor", "TFT_Item_BrambleVest"], "items": [66, 77, 55], "name": "", "rarity": 2, "tier": 2}, {"character_id": "TFT8_Rammus", "itemNames": [], "items": [], "name": "", "rarity": 2, "tier": 2}, {"character_id": "TFT8_BelVeth", "itemNames": ["TFT8_Item_DeadeyeEmblemItem", "TFT_Item_MadredsBloodrazor", "TFT_Item_RunaansHurricane"], "items": [8018, 12, 26], "name": "", "rarity": 4, "tier": 2}, {"character_id": "TFT8_AurelionSol", "itemNames": [], "items": [], "name": "", "rarity": 4, "tier": 1}, {"character_id": "TFT8_Zac", "itemNames": [], "items": [], "name": "", "rarity": 4, "tier": 2}]}], "queue_id": 1090, "tft_game_type": "standard", "tft_set_core_name": "TFTSet8", "tft_set_number": 8}}